nrfcredstore/__init__.py
nrfcredstore/cli.py
nrfcredstore/command_interface.py
nrfcredstore/comms.py
nrfcredstore/credstore.py
nrfcredstore/exceptions.py
nrfcredstore-2.0.9.dist-info/METADATA
nrfcredstore-2.0.9.dist-info/WHEEL
nrfcredstore-2.0.9.dist-info/entry_points.txt
nrfcredstore-2.0.9.dist-info/licenses/LICENSE
nrfcredstore-2.0.9.dist-info/RECORD
