Metadata-Version: 2.4
Name: nrfcredstore
Version: 2.0.9
Summary: Manage credentials stored in Nordic Semiconductor modems.
License: BSD-3-Clause
License-File: LICENSE
Author: Nordic Semiconductor ASA
Requires-Python: >=3.10,<4.0
Classifier: License :: OSI Approved :: BSD License
Classifier: Programming Language :: Python :: 3
Classifier: Programming Language :: Python :: 3.10
Classifier: Programming Language :: Python :: 3.11
Classifier: Programming Language :: Python :: 3.12
Classifier: Programming Language :: Python :: 3.13
Classifier: Programming Language :: Python :: 3.14
Requires-Dist: coloredlogs (>=15.0.1,<16.0.0)
Requires-Dist: inquirer (>=3.4.0,<4.0.0)
Requires-Dist: pynrfjprog (>=10.23.0,<11.0.0)
Requires-Dist: pyserial (>=3.5,<4.0)
Project-URL: Repository, https://github.com/NordicSemiconductor/nrfcredstore
